Metadata-Version: 2.1
Name: ComputationalGraph-Py
Version: 1.0.0
Summary: Computational Graph library
Home-page: https://github.com/StarlangSoftware/ComputationalGraph-Py
Author: olcaytaner
Author-email: olcay.yildiz@ozyegin.edu.tr
